{
    "bit_outputs": [
        [
            "163",
            "161",
            "162",
            "172",
            "165"
        ]
    ],
    "enable_input_regs": false,
    "enable_output_regs": false,
    "input_width": 16,
    "modules": [
        {
            "id": "0",
            "type": "const"
        },
        {
            "id": "1",
            "in0": [
                "84"
            ],
            "in1": [
                "0",
                "158"
            ],
            "type": "mul"
        },
        {
            "id": "156",
            "in0": [
                "84"
            ],
            "in1": [
                "158"
            ],
            "type": "add"
        },
        {
            "id": "157",
            "in0": [
                "159"
            ],
            "in1": [
                "0",
                "84",
                "156"
            ],
            "type": "add"
        },
        {
            "id": "160",
            "in0": [
                "84"
            ],
            "in1": [
                "158"
            ],
            "type": "absd"
        },
        {
            "id": "161",
            "in0": [
                "84"
            ],
            "in1": [
                "158"
            ],
            "type": "lte"
        },
        {
            "id": "162",
            "in0": [
                "84"
            ],
            "in1": [
                "158"
            ],
            "type": "gte"
        },
        {
            "id": "163",
            "in0": [
                "84"
            ],
            "in1": [
                "158"
            ],
            "type": "sub"
        },
        {
            "id": "164",
            "in0": [
                "84"
            ],
            "in1": [
                "158"
            ],
            "type": "shr"
        },
        {
            "id": "165",
            "in0": [
                "166"
            ],
            "in1": [
                "167"
            ],
            "in2": [
                "168"
            ],
            "type": "lut"
        },
        {
            "id": "170",
            "in0": [
                "84"
            ],
            "in1": [
                "158"
            ],
            "type": "bit_alu"
        },
        {
            "id": "171",
            "in0": [
                "159"
            ],
            "in1": [
                "84"
            ],
            "in2": [
                "166"
            ],
            "type": "mux"
        },
        {
            "id": "172",
            "type": "bitconst"
        }
    ],
    "output_width": 16,
    "outputs": [
        [
            "163",
            "157",
            "0",
            "161",
            "162",
            "170",
            "171",
            "1",
            "164",
            "160"
        ]
    ]
}